confluent_kafka_helpers/__init__.py
confluent_kafka_helpers/callbacks.py
confluent_kafka_helpers/consumer.py
confluent_kafka_helpers/context.py
confluent_kafka_helpers/exceptions.py
confluent_kafka_helpers/loader.py
confluent_kafka_helpers/message.py
confluent_kafka_helpers/producer.py
confluent_kafka_helpers/schema_registry.py
confluent_kafka_helpers/utils.py
confluent_kafka_helpers/metrics/__init__.py
confluent_kafka_helpers/metrics/callbacks.py
confluent_kafka_helpers/metrics/statistics.py
confluent_kafka_helpers/tracing/__init__.py
confluent_kafka_helpers/tracing/attributes.py
confluent_kafka_helpers/tracing/datadog.py
confluent_kafka_helpers/tracing/opentelemetry.py
tests/__init__.py
tests/config.py
tests/conftest.py
tests/kafka.py
tests/test_callbacks.py
tests/test_consumer.py
tests/test_loader.py
tests/test_message.py
tests/test_producer.py
tests/test_schema_registry.py
tests/test_utils.py
confluent_kafka_helpers-1.1.2.dist-info/METADATA
confluent_kafka_helpers-1.1.2.dist-info/WHEEL
confluent_kafka_helpers-1.1.2.dist-info/top_level.txt
confluent_kafka_helpers-1.1.2.dist-info/RECORD
