Metadata-Version: 2.4
Name: confluent-kafka-helpers
Version: 1.1.2
Summary: Helpers for Confluent's Kafka Python client
Home-page: https://github.com/fyndiq/confluent_kafka_helpers
Author: Fyndiq AB
Author-email: support@fyndiq.com
License: MIT
Requires-Dist: structlog>=17.2.0
Requires-Dist: confluent-kafka[avro]==2.*
Requires-Dist: opentelemetry-api==1.27.0
Requires-Dist: opentelemetry-semantic-conventions==0.48b0
Dynamic: author
Dynamic: author-email
Dynamic: home-page
Dynamic: license
Dynamic: requires-dist
Dynamic: summary
